{
  "store": {
    "name": "Stock-Sync Pro",
    "location": "Vancouver Distribution Centre",
    "manager": "Sarah Chen",
    "lastSync": "2025-03-24T08:45:00Z"
  },
  "summary": {
    "totalSKUs": 248,
    "lowStockItems": 12,
    "outOfStockItems": 3,
    "totalValue": 184320.50,
    "pendingOrders": 7
  },
  "categories": [
    { "id": "cat-1", "name": "Dairy & Eggs", "skuCount": 42, "value": 28400.00 },
    { "id": "cat-2", "name": "Produce", "skuCount": 61, "value": 19200.00 },
    { "id": "cat-3", "name": "Bakery", "skuCount": 28, "value": 11800.00 },
    { "id": "cat-4", "name": "Beverages", "skuCount": 55, "value": 38900.00 },
    { "id": "cat-5", "name": "Frozen Foods", "skuCount": 37, "value": 42500.00 },
    { "id": "cat-6", "name": "Snacks & Confectionery", "skuCount": 25, "value": 43520.50 }
  ],
  "products": [
    {
      "id": "SKU-10021",
      "name": "Organic Whole Milk 4L",
      "category": "Dairy & Eggs",
      "vendor": "Avalon Dairy",
      "price": 7.49,
      "stock": 142,
      "safetyStock": 50,
      "reorderPoint": 80,
      "leadTimeDays": 2,
      "status": "ok",
      "lastSold": "2025-03-24T07:10:00Z",
      "weeklyVelocity": 98
    },
    {
      "id": "SKU-10034",
      "name": "Free-Range Eggs 12pk",
      "category": "Dairy & Eggs",
      "vendor": "Happy Hens Farm",
      "price": 5.99,
      "stock": 38,
      "safetyStock": 40,
      "reorderPoint": 60,
      "leadTimeDays": 3,
      "status": "low",
      "lastSold": "2025-03-24T08:22:00Z",
      "weeklyVelocity": 75
    },
    {
      "id": "SKU-20011",
      "name": "Bananas (per bunch)",
      "category": "Produce",
      "vendor": "Pacific Fresh Co.",
      "price": 1.89,
      "stock": 0,
      "safetyStock": 30,
      "reorderPoint": 50,
      "leadTimeDays": 1,
      "status": "out",
      "lastSold": "2025-03-24T06:55:00Z",
      "weeklyVelocity": 210
    },
    {
      "id": "SKU-20045",
      "name": "Roma Tomatoes 1kg",
      "category": "Produce",
      "vendor": "Pacific Fresh Co.",
      "price": 3.29,
      "stock": 87,
      "safetyStock": 25,
      "reorderPoint": 40,
      "leadTimeDays": 1,
      "status": "ok",
      "lastSold": "2025-03-24T07:40:00Z",
      "weeklyVelocity": 55
    },
    {
      "id": "SKU-30002",
      "name": "Sourdough Loaf",
      "category": "Bakery",
      "vendor": "West Coast Bakers",
      "price": 4.99,
      "stock": 24,
      "safetyStock": 20,
      "reorderPoint": 30,
      "leadTimeDays": 1,
      "status": "low",
      "lastSold": "2025-03-24T08:00:00Z",
      "weeklyVelocity": 60
    },
    {
      "id": "SKU-40019",
      "name": "Orange Juice 1.89L",
      "category": "Beverages",
      "vendor": "Tropicana",
      "price": 6.49,
      "stock": 215,
      "safetyStock": 60,
      "reorderPoint": 100,
      "leadTimeDays": 4,
      "status": "ok",
      "lastSold": "2025-03-24T08:30:00Z",
      "weeklyVelocity": 120
    },
    {
      "id": "SKU-40033",
      "name": "Sparkling Water 12pk",
      "category": "Beverages",
      "vendor": "San Pellegrino",
      "price": 9.99,
      "stock": 18,
      "safetyStock": 24,
      "reorderPoint": 36,
      "leadTimeDays": 5,
      "status": "low",
      "lastSold": "2025-03-24T07:15:00Z",
      "weeklyVelocity": 32
    },
    {
      "id": "SKU-50007",
      "name": "Frozen Pizza Pepperoni",
      "category": "Frozen Foods",
      "vendor": "Dr. Oetker",
      "price": 8.49,
      "stock": 0,
      "safetyStock": 30,
      "reorderPoint": 48,
      "leadTimeDays": 6,
      "status": "out",
      "lastSold": "2025-03-23T18:44:00Z",
      "weeklyVelocity": 88
    },
    {
      "id": "SKU-50021",
      "name": "Mixed Vegetables 750g",
      "category": "Frozen Foods",
      "vendor": "Green Giant",
      "price": 4.29,
      "stock": 63,
      "safetyStock": 30,
      "reorderPoint": 50,
      "leadTimeDays": 6,
      "status": "ok",
      "lastSold": "2025-03-24T07:55:00Z",
      "weeklyVelocity": 45
    },
    {
      "id": "SKU-60008",
      "name": "Lay's Classic Chips 200g",
      "category": "Snacks & Confectionery",
      "vendor": "Frito-Lay",
      "price": 3.79,
      "stock": 192,
      "safetyStock": 50,
      "reorderPoint": 80,
      "leadTimeDays": 5,
      "status": "ok",
      "lastSold": "2025-03-24T08:40:00Z",
      "weeklyVelocity": 145
    },
    {
      "id": "SKU-60015",
      "name": "Dark Chocolate Bar 100g",
      "category": "Snacks & Confectionery",
      "vendor": "Lindt",
      "price": 5.49,
      "stock": 9,
      "safetyStock": 20,
      "reorderPoint": 30,
      "leadTimeDays": 7,
      "status": "low",
      "lastSold": "2025-03-24T07:30:00Z",
      "weeklyVelocity": 28
    },
    {
      "id": "SKU-20088",
      "name": "Baby Spinach 142g",
      "category": "Produce",
      "vendor": "Earthbound Farm",
      "price": 4.99,
      "stock": 0,
      "safetyStock": 20,
      "reorderPoint": 35,
      "leadTimeDays": 2,
      "status": "out",
      "lastSold": "2025-03-24T06:30:00Z",
      "weeklyVelocity": 55
    },
    {
      "id": "SKU-10056",
      "name": "Greek Yogurt 650g",
      "category": "Dairy & Eggs",
      "vendor": "Oikos",
      "price": 6.99,
      "stock": 44,
      "safetyStock": 30,
      "reorderPoint": 50,
      "leadTimeDays": 3,
      "status": "low",
      "lastSold": "2025-03-24T08:10:00Z",
      "weeklyVelocity": 62
    },
    {
      "id": "SKU-40055",
      "name": "Cold Brew Coffee 4pk",
      "category": "Beverages",
      "vendor": "Starbucks",
      "price": 12.99,
      "stock": 76,
      "safetyStock": 20,
      "reorderPoint": 40,
      "leadTimeDays": 5,
      "status": "ok",
      "lastSold": "2025-03-24T08:05:00Z",
      "weeklyVelocity": 38
    },
    {
      "id": "SKU-30018",
      "name": "Croissants 6pk",
      "category": "Bakery",
      "vendor": "West Coast Bakers",
      "price": 5.49,
      "stock": 55,
      "safetyStock": 15,
      "reorderPoint": 25,
      "leadTimeDays": 1,
      "status": "ok",
      "lastSold": "2025-03-24T07:48:00Z",
      "weeklyVelocity": 72
    }
  ],
  "recentActivity": [
    { "id": "act-1", "type": "restock", "sku": "SKU-40019", "name": "Orange Juice 1.89L", "quantity": 120, "timestamp": "2025-03-24T06:00:00Z" },
    { "id": "act-2", "type": "alert", "sku": "SKU-20011", "name": "Bananas (per bunch)", "message": "Out of stock — auto PO raised", "timestamp": "2025-03-24T07:00:00Z" },
    { "id": "act-3", "type": "sale", "sku": "SKU-60008", "name": "Lay's Classic Chips 200g", "quantity": 24, "timestamp": "2025-03-24T07:30:00Z" },
    { "id": "act-4", "type": "alert", "sku": "SKU-10034", "name": "Free-Range Eggs 12pk", "message": "Below reorder point", "timestamp": "2025-03-24T08:00:00Z" },
    { "id": "act-5", "type": "restock", "sku": "SKU-10021", "name": "Organic Whole Milk 4L", "quantity": 48, "timestamp": "2025-03-24T08:30:00Z" }
  ]
}